autoguard/__init__.py
autoguard/config_helpers.py
autoguard/example_settings.ini
autoguard/ldap.py
autoguard/runner.py
autoguard/sentry_conf.py
autoguard/tests.py
autoguard-0.3.4.dist-info/DESCRIPTION.rst
autoguard-0.3.4.dist-info/METADATA
autoguard-0.3.4.dist-info/RECORD
autoguard-0.3.4.dist-info/WHEEL
autoguard-0.3.4.dist-info/entry_points.txt
autoguard-0.3.4.dist-info/metadata.json
autoguard-0.3.4.dist-info/pbr.json
autoguard-0.3.4.dist-info/top_level.txt
