Metadata-Version: 2.0
Name: autoguard
Version: 0.3.4
Summary: Configuration setup for sentry
Home-page: https://github.com/Polyconseil/autoguard
Author: Polyconseil
Author-email: opensource+autoguard@polyconseil.fr
License: BSD
Keywords: sentry config
Platform: UNKNOWN
Classifier: Development Status :: 3 - Alpha
Classifier: Intended Audience :: Developers
Classifier: License :: OSI Approved :: BSD License
Classifier: Topic :: Software Development :: Build Tools
Classifier: Programming Language :: Python :: 2
Classifier: Programming Language :: Python :: 2.7
Requires-Dist: getconf (>=1.4.1)
Requires-Dist: nydus (>=0.11.0,<0.12.0)
Requires-Dist: python-ldap (>=2.4.19)
Requires-Dist: python-memcached (>=1.54)
Requires-Dist: sentry[postgres] (==8.3.0)
